{
  "inspire_id": 838712,
  "title": "The r-modes of rotating fluids",
  "year": 2007,
  "citations": [
    {
      "inspire_id": 122127,
      "citation_count": 1001,
      "title": "Raumzeitkonzeptionen in der Quantengravitation (Spacetime in Quantum Gravity)",
      "year": 2008
    },
    {
      "inspire_id": 122126,
      "citation_count": 25,
      "title": "Raumzeitkonzeptionen in der Quantengravitation (Spacetime in Quantum Gravity)",
      "year": 2008
    },
    {
      "inspire_id": 122120,
      "citation_count": 25,
      "title": "Raumzeitkonzeptionen in der Quantengravitation (Spacetime in Quantum Gravity)",
      "year": 2009
    },
    {
      "inspire_id": 122120,
      "citation_count": 15,
      "title": "Raumzeitkonzeptionen in der Quantengravitation (Spacetime in Quantum Gravity)",
      "year": 2015
    }
  ],
  "references": [
    {
      "inspire_id": 122121,
      "citation_count": 12,
      "title": "The Elegant Universe Superstrings, Hidden Dimensions, and the Quest for the Ultimate Theory",
      "year": 1999
    },
    {
      "inspire_id": 122122,
      "citation_count": 6,
      "title": "Superstrings A Theory of Everything?",
      "year": 1988
    },
    {
      "inspire_id": 122123,
      "citation_count": 2,
      "title": "The Trouble with Physics The Rise of String Theory, the Fall of a Science, and What Comes Next",
      "year": 2006
    },
    {
      "inspire_id": 122124,
      "citation_count": 19,
      "title": "Yang-Mills and the Mass Gap",
      "year": 2005
    }
  ]
}